acelerai_inputstream/__init__.py
acelerai_inputstream/inputstream.py
acelerai_inputstream/inputstream_client.py
acelerai_package-0.0.2.dist-info/METADATA
acelerai_package-0.0.2.dist-info/WHEEL
acelerai_package-0.0.2.dist-info/top_level.txt
acelerai_package-0.0.2.dist-info/RECORD
